LICENSE
README.md
pyproject.toml
setup.py
getllms/__init__.py
getllms/__main__.py
getllms/cli.py
getllms/core.py
getllms/data.py
getllms/download.py
getllms/model.py
getllms.egg-info/PKG-INFO
getllms.egg-info/SOURCES.txt
getllms.egg-info/dependency_links.txt
getllms.egg-info/entry_points.txt
getllms.egg-info/requires.txt
getllms.egg-info/top_level.txt