Metadata-Version: 2.1
Name: getllms
Version: 1.2
Summary: Download LLMs to use locally.
Author-email: AWeirdDev <aweirdscratcher@gmail.com>
License:                                  Apache License
Project-URL: Source, https://github.com/AWeirdScratcher/getllms
Project-URL: Bug Tracker, https://github.com/AWeirdScratcher/getllms/issues
Keywords: getllms,llm,llms,index,download,ai,gpt,llama
Classifier: Programming Language :: Python :: 3
Classifier: License :: OSI Approved :: MIT License
Classifier: Operating System :: OS Independent
Requires-Python: >=3.8
License-File: LICENSE
Requires-Dist: requests
Requires-Dist: holdon
